w/__init__.py
w/apps.py
w/data_test_factory/README.md
w/data_test_factory/__init__.py
w/data_test_factory/data_test_factory.py
w/ddd/__init__.py
w/ddd/entity.py
w/ddd/repository.py
w/ddd/test_utils/__init__.py
w/ddd/test_utils/abstract_tdf.py
w/debug.py
w/django/__init__.py
w/django/commands/__init__.py
w/django/commands/abstract_maintenance_mode_command.py
w/django/models.py
w/django/services/__init__.py
w/django/services/business/__init__.py
w/django/services/business/user_service.py
w/django/templatetags/__init__.py
w/django/templatetags/util_filters.py
w/django/tests/__init__.py
w/django/tests/builders/__init__.py
w/django/tests/builders/user_test_builder.py
w/django/tests/django_testcase.py
w/django/tests/factories/__init__.py
w/django/tests/factories/auth_factories.py
w/django/tests/factories/reference_factory.py
w/django/tests/view_testcase.py
w/django/utils.py
w/django/w_command.py
w/drf/__init__.py
w/drf/decorators/__init__.py
w/drf/decorators/group_required.py
w/drf/exception_handler.py
w/drf/jwt/__init__.py
w/drf/jwt/jwt_authentication_backend.py
w/drf/jwt/jwt_viewset.py
w/drf/jwt/login_viewset.py
w/drf/middlewares/__init__.py
w/drf/middlewares/cypress_middleware.py
w/drf/middlewares/maintenance_mode_middleware.py
w/drf/mixins.py
w/drf/serializers/__init__.py
w/drf/serializers/fields.py
w/drf/serializers/mixins.py
w/drf/serializers/serpy_serializers.py
w/drf/sso/__init__.py
w/drf/sso/sso_auth_backend.py
w/drf/sso/sso_user_mixin.py
w/drf/tests/__init__.py
w/drf/tests/api_testcase.py
w/drf/tests/helpers/__init__.py
w/drf/tests/helpers/jwt/__init__.py
w/drf/tests/helpers/jwt/jwt_test_helper.py
w/drf/tests/viewsets/abstract_cypress_viewset.py
w/drf/validators/__init__.py
w/drf/validators/drf_validator.py
w/drf/viewsets.py
w/enums.py
w/exceptions.py
w/mixins/__init__.py
w/mixins/dataclasses_mixin.py
w/mixins/thread_mixin.py
w/pydantics/date_models.py
w/serializers/__init__.py
w/serializers/serializer.md
w/serializers/serializer.py
w/services/__init__.py
wedge_lib-3.1.29.dist-info/METADATA
wedge_lib-3.1.29.dist-info/WHEEL
wedge_lib-3.1.29.dist-info/licenses/LICENSE.txt
wedge_lib-3.1.29.dist-info/RECORD
