Metadata-Version: 2.4
Name: wedge-lib
Version: 3.1.29
Summary: Wedge library for django application
License: MIT
License-File: LICENSE.txt
Author: François Schneider
Author-email: francois.schneider@wedge-digital.com
Requires-Python: >=3.12,<4.0
Classifier: License :: OSI Approved :: MIT License
Classifier: Programming Language :: Python :: 3
Classifier: Programming Language :: Python :: 3.12
Classifier: Programming Language :: Python :: 3.13
Classifier: Programming Language :: Python :: 3.14
Requires-Dist: argon2-cffi
Requires-Dist: arrow
Requires-Dist: cryptography
Requires-Dist: django
Requires-Dist: django-sms (>=0.7.0,<0.8.0)
Requires-Dist: djangorestframework
Requires-Dist: djangorestframework-api-key
Requires-Dist: mergedeep
Requires-Dist: openpyxl
Requires-Dist: pandas
Requires-Dist: python-dateutil
Requires-Dist: python-keycloak
Requires-Dist: python-ulid (>=3.0.0,<4.0.0)
Requires-Dist: pyyaml (>=6.0.3)
Requires-Dist: pyzstd
Requires-Dist: requests
Requires-Dist: serpy
Requires-Dist: validators
Requires-Dist: var-dump
